weatherflow/__init__.py
weatherflow/test_flow_trainer.py
weatherflow/version.py
weatherflow/data/__init__.py
weatherflow/data/datasets.py
weatherflow/data/datasets.py.backup
weatherflow/data/era5.py
weatherflow/data/sequence.py
weatherflow/data/streaming.py
weatherflow/data/webdataset_loader.py
weatherflow/education/__init__.py
weatherflow/education/graduate_tool.py
weatherflow/manifolds/__init__.py
weatherflow/manifolds/sphere.py
weatherflow/models/__init__.py
weatherflow/models/base.py
weatherflow/models/conversion.py
weatherflow/models/flow_matching.py
weatherflow/models/icosahedral.py
weatherflow/models/physics_guided.py
weatherflow/models/score_matching.py
weatherflow/models/stochastic.py
weatherflow/models/weather_flow.py
weatherflow/path/__init__.py
weatherflow/path/condot_path.py
weatherflow/path/gaussian_path.py
weatherflow/path/geodesic.py
weatherflow/path/prob_path.py
weatherflow/path/schedulers/__init__.py
weatherflow/physics/__init__.py
weatherflow/physics/atmospheric.py
weatherflow/physics/losses.py
weatherflow/server/__init__.py
weatherflow/server/app.py
weatherflow/simulation/__init__.py
weatherflow/simulation/orchestrator.py
weatherflow/solvers/__init__.py
weatherflow/solvers/langevin.py
weatherflow/solvers/ode_solver.py
weatherflow/solvers/riemannian.py
weatherflow/training/__init__.py
weatherflow/training/flow_trainer.py
weatherflow/training/metrics.py
weatherflow/training/trainers.py
weatherflow/training/utils.py
weatherflow/utils/__init__.py
weatherflow/utils/cloud_rendering.py
weatherflow/utils/evaluation.py
weatherflow/utils/flow_visualization.py
weatherflow/utils/skewt.py
weatherflow/utils/visualization.py
weatherflow-0.4.3.dist-info/METADATA
weatherflow-0.4.3.dist-info/WHEEL
weatherflow-0.4.3.dist-info/licenses/LICENSE
weatherflow-0.4.3.dist-info/RECORD
