Metadata-Version: 2.4
Name: weatherflow
Version: 0.4.3
Summary: Physics-guided flow models for weather prediction with flow matching
Project-URL: Homepage, https://github.com/monksealseal/weatherflow
Project-URL: Bug Tracker, https://github.com/monksealseal/weatherflow/issues
Author-email: monksealseal <esiman@msn.com>
License: MIT
License-File: LICENSE
Requires-Python: >=3.8
Requires-Dist: bottleneck>=1.3.6
Requires-Dist: cartopy>=0.21
Requires-Dist: cdsapi>=0.6.1
Requires-Dist: fastapi<0.112.0,>=0.110.0
Requires-Dist: flask>=3.0.0
Requires-Dist: fsspec>=2023.9.0
Requires-Dist: gcsfs>=2023.9.0
Requires-Dist: gunicorn>=21.2.0
Requires-Dist: h5py>=3.0.0
Requires-Dist: matplotlib>=3.7.0
Requires-Dist: netcdf4>=1.5.7
Requires-Dist: numpy<2.0.0,>=1.24.0
Requires-Dist: pandas>=1.5.0
Requires-Dist: pillow>=9.0.0
Requires-Dist: plotly>=5.18.0
Requires-Dist: pyyaml>=6.0
Requires-Dist: scipy>=1.7.0
Requires-Dist: torch>=2.0.0
Requires-Dist: torchdiffeq>=0.2.3
Requires-Dist: tqdm
Requires-Dist: uvicorn<0.28.0,>=0.23.0
Requires-Dist: wandb
Requires-Dist: webdataset>=0.2.86
Requires-Dist: xarray>=2023.1.0
Requires-Dist: zarr<3.0.0,>=2.14.2
Provides-Extra: dev
Requires-Dist: black>=23.3.0; extra == 'dev'
Requires-Dist: flake8-docstrings>=1.7.0; extra == 'dev'
Requires-Dist: flake8>=6.0.0; extra == 'dev'
Requires-Dist: isort>=5.12.0; extra == 'dev'
Requires-Dist: mypy>=1.3.0; extra == 'dev'
Requires-Dist: pre-commit>=3.3.3; extra == 'dev'
Requires-Dist: pytest-cov>=4.1.0; extra == 'dev'
Requires-Dist: pytest>=7.3.1; extra == 'dev'
Provides-Extra: docs
Requires-Dist: mkdocs-jupyter>=0.24.0; extra == 'docs'
Requires-Dist: mkdocs-material>=9.0.0; extra == 'docs'
Requires-Dist: mkdocstrings-python>=0.9.0; extra == 'docs'
Requires-Dist: mkdocstrings>=0.20.0; extra == 'docs'
